setup.py
src/automation/__init__.py
src/automation/deploy.py
src/automation/helpers.py
src/automation/pull_request.py
src/automation/refresh.py
src/automation/stage.py
src/automation/sync.py
src/automation/topic.py
src/automation.egg-info/PKG-INFO
src/automation.egg-info/SOURCES.txt
src/automation.egg-info/dependency_links.txt
src/automation.egg-info/not-zip-safe
src/automation.egg-info/requires.txt
src/automation.egg-info/top_level.txt