Metadata-Version: 1.1
Name: automation
Version: 0.5.4
Summary: A Django-specific implementation of Fabric
Home-page: https://github.com/dustinfarris/automation
Author: Dustin Farris
Author-email: dustin@dustinfarris.com
License: BSD
Platform: UNKNOWN
Classifier: Framework :: Django
Classifier: Intended Audience :: System Administrators
Classifier: Operating System :: Unix
Classifier: Topic :: Internet :: WWW/HTTP :: HTTP Servers
Classifier: Topic :: Software Development :: Version Control
Classifier: Topic :: Software Development :: Quality Assurance
